kanichart/__init__.py
kanichart/_chart.py
kanichart/files/load.jinja
kanichart/files/theme.js
kanichart-0.1.4.dist-info/DESCRIPTION.rst
kanichart-0.1.4.dist-info/METADATA
kanichart-0.1.4.dist-info/RECORD
kanichart-0.1.4.dist-info/WHEEL
kanichart-0.1.4.dist-info/metadata.json
kanichart-0.1.4.dist-info/top_level.txt
tests/__init__.py
tests/test_sample.py
