Metadata-Version: 2.0
Name: kanichart
Version: 0.1.4
Summary: Kan i(簡易) chart. Easy plotting library.
Home-page: https://github.com/fx-kirin/kanichart
Author: Yoshiaki Ono
Author-email: ono.kirin@gmail.com
License: UNKNOWN
Platform: UNKNOWN
Classifier: Development Status :: 2 - Pre-Alpha
Classifier: Programming Language :: Python
Classifier: Programming Language :: Python :: 2
Classifier: Programming Language :: Python :: 2.7
Classifier: Programming Language :: Python :: 3
Classifier: Programming Language :: Python :: 3.4
Classifier: Programming Language :: Python :: 3.5
Requires-Dist: jinja2
Requires-Dist: pandas
Requires-Dist: python-highcharts
